{
  "$schema": "https://developer.microsoft.com/json-schemas/fabric/item/report/definition/visualContainer/2.4.0/schema.json",
  "name": "8edd789a12532e6ee81a",
  "position": {
    "x": 191.79720367353514,
    "y": 626.89271200701762,
    "z": 13000,
    "height": 30.190300578241644,
    "width": 321.43790615657281,
    "tabOrder": 13000
  },
  "visual": {
    "visualType": "textbox",
    "objects": {
      "general": [
        {
          "properties": {
            "paragraphs": [
              {
                "textRuns": [
                  {
                    "value": "CAPITAL ADECUADO",
                    "textStyle": {
                      "fontWeight": "bold",
                      "fontSize": "12pt",
                      "color": "#666666"
                    }
                  }
                ]
              }
            ]
          }
        }
      ]
    },
    "visualContainerObjects": {
      "background": [
        {
          "properties": {
            "show": {
              "expr": {
                "Literal": {
                  "Value": "false"
                }
              }
            }
          }
        }
      ]
    },
    "drillFilterOtherVisuals": true
  }
}